{
  "06 Venus Transit": [
    {
      "file": "200601_Venus_transit_1st_House_from_natal_moon.md",
      "title": "Venus transit 1st House from natal moon",
      "order": 200601
    },
    {
      "file": "200602_Venus_transit_2nd_House_from_natal_moon.md",
      "title": "Venus transit 2nd House from natal moon",
      "order": 200602
    },
    {
      "file": "200603_Venus_transit_3rd_House_from_natal_moon.md",
      "title": "Venus transit 3rd House from natal moon",
      "order": 200603
    },
    {
      "file": "200604_Venus_transit_4th_House_from_natal_moon.md",
      "title": "Venus transit 4th House from natal moon",
      "order": 200604
    },
    {
      "file": "200605_Venus_transit_5th_House_from_natal_moon.md",
      "title": "Venus transit 5th House from natal moon",
      "order": 200605
    },
    {
      "file": "200606_Venus_transit_6th_House_from_natal_moon.md",
      "title": "Venus transit 6th House from natal moon",
      "order": 200606
    },
    {
      "file": "200607_Venus_transit_7th_House_from_natal_moon.md",
      "title": "Venus transit 7th House from natal moon",
      "order": 200607
    },
    {
      "file": "200608_Venus_transit_8th_House_from_natal_moon.md",
      "title": "Venus transit 8th House from natal moon",
      "order": 200608
    },
    {
      "file": "200609_Venus_transit_9th_House_from_natal_moon.md",
      "title": "Venus transit 9th House from natal moon",
      "order": 200609
    },
    {
      "file": "200610_Venus_transit_10th_House_from_natal_moon.md",
      "title": "Venus transit 10th House from natal moon",
      "order": 200610
    },
    {
      "file": "200611_Venus_transit_11th_House_from_natal_moon.md",
      "title": "Venus transit 11th House from natal moon",
      "order": 200611
    },
    {
      "file": "200612_Venus_transit_12th_House_from_natal_moon.md",
      "title": "Venus transit 12th House from natal moon",
      "order": 200612
    }
  ]
}